align_phonemes/__init__.py
align_phonemes/get_forced_alignments.py
align_phonemes/test.py
align_phonemes/src/__init__.py
align_phonemes/src/apply_transcriptions.py
align_phonemes/src/evaluate.py
align_phonemes/src/wav2vec.py
align_phonemes/utils/__init__.py
align_phonemes/utils/clean_directories.py
align_phonemes/utils/demarcate_to_json.py
align_phonemes/utils/find_files.py
align_phonemes/utils/parse_block.py
align_phonemes/utils/run_mfa.py
align_phonemes-0.12.dist-info/METADATA
align_phonemes-0.12.dist-info/WHEEL
align_phonemes-0.12.dist-info/top_level.txt
align_phonemes-0.12.dist-info/RECORD
